frankensvg/__init__.py
frankensvg/cli.py
frankensvg-0.0.1.dist-info/DESCRIPTION.rst
frankensvg-0.0.1.dist-info/METADATA
frankensvg-0.0.1.dist-info/RECORD
frankensvg-0.0.1.dist-info/WHEEL
frankensvg-0.0.1.dist-info/entry_points.txt
frankensvg-0.0.1.dist-info/metadata.json
frankensvg-0.0.1.dist-info/top_level.txt
